[
  {
    "text": "哪種交通工具最容易被嘴？火車，因為它欠嗆欠嗆欠嗆。",
    "category": "諧音梗",
    "author": ""
  },
  {
    "text": "哪裡最常看到長頸鹿？考場。",
    "category": "冷笑話",
    "author": ""
  },
  {
    "text": "樹的味道像什麼？數味像雞（數位相機）。",
    "category": "諧音梗",
    "author": ""
  },
  {
    "text": "什麼水果最燙？梨子，因為離子燙。",
    "category": "諧音梗",
    "author": ""
  },
  {
    "text": "皇帝的五個老婆都是大胃王，猜飲料牌子。答：五后食光。",
    "category": "諧音梗",
    "author": ""
  },
  {
    "text": "全台灣哪個縣市的人最容易跌倒？新竹，因為很多絆倒體（半導體）。",
    "category": "台灣特色",
    "author": ""
  },
  {
    "text": "哪裡的房子最小？嘉義，因為嘉義戶小。",
    "category": "台灣特色",
    "author": ""
  },
  {
    "text": "用南瓜打頭和用西瓜打頭，哪個比較痛？頭比較痛。",
    "category": "腦筋急轉彎",
    "author": ""
  },
  {
    "text": "老王、老張跟老陳開車闖紅燈，誰會被開單？老王，因為罰老王。",
    "category": "諧音梗",
    "author": ""
  },
  {
    "text": "透明的劍是什麼劍？無人見（劍）。",
    "category": "諧音梗",
    "author": ""
  },
  {
    "text": "麵包超人扭到腳會變成什麼？牛角麵包（扭腳麵包）。",
    "category": "諧音梗",
    "author": ""
  },
  {
    "text": "四的敵人是誰？黑松，因為黑松殺四（沙士）。",
    "category": "諧音梗",
    "author": ""
  },
  {
    "text": "哪個朝代的人最可愛？元朝，因為他們都是萌古人（蒙古人）。",
    "category": "諧音梗",
    "author": ""
  },
  {
    "text": "台灣每過一分鐘，非洲會發生什麼事？他們過了六十秒。",
    "category": "冷笑話",
    "author": ""
  },
  {
    "text": "液晶的媽媽叫什麼名字？液晶螢幕（易經的媽媽）。",
    "category": "諧音梗",
    "author": ""
  },
  {
    "text": "雅婷是最菜市場的名字，那最夜市的名字呢？雅琪（夜棲）。",
    "category": "諧音梗",
    "author": ""
  },
  {
    "text": "男子：「你長得像香蕉嗎？」女子：「很像！」男子：「那你就是我的妻子。」（如蕉似妻—如膠似漆）",
    "category": "諧音梗",
    "author": ""
  },
  {
    "text": "小美懷著夢想來到台北，十個月後她就生下了夢想。",
    "category": "冷笑話",
    "author": ""
  },
  {
    "text": "有天看到媽媽用市話打來，我就很生氣地說：「打賴啦媽！」我媽錯愕地說：「我不是達賴喇嘛…」",
    "category": "諧音梗",
    "author": ""
  },
  {
    "text": "剛剛在做蛋糕，我媽叫我打發鮮奶油，我就隨便跟鮮奶油聊了幾句跟它說再見。",
    "category": "冷笑話",
    "author": ""
  },
  {
    "text": "湖口跟林口暢聊了一個晚上，感嘆地說：「哇我們真的有交流道欸。」",
    "category": "台灣特色",
    "author": ""
  },
  {
    "text": "有一天下午，一個台北的學校正在頒獎，主席說：「受獎人請到台中。」受獎人就跑到台中了。",
    "category": "台灣特色",
    "author": ""
  },
  {
    "text": "為什麼北投叫北投？因為南是角（南勢角）。",
    "category": "台灣特色",
    "author": ""
  },
  {
    "text": "基隆天天下雨辦公室很潮濕，老闆皺眉說：「為什麼不開除濕機？」然後秘書就開除司機了。",
    "category": "職場笑話",
    "author": ""
  },
  {
    "text": "L的過去式是什麼？LED。",
    "category": "冷笑話",
    "author": ""
  },
  {
    "text": "請用in put造句。觀世in put薩。",
    "category": "諧音梗",
    "author": ""
  },
  {
    "text": "台灣哪個便利商店一進去就被趕出來？萊爾富，因為Hi-Life（還來！）",
    "category": "台灣特色",
    "author": ""
  },
  {
    "text": "誰家沒有電話？天衣，因為天衣無縫（phone）。",
    "category": "諧音梗",
    "author": ""
  },
  {
    "text": "有一天Y跟X走在路上，突然看到U哭得很傷心，Y就走過去問U說：「Uniqlo（U你哭囉）！」",
    "category": "諧音梗",
    "author": ""
  },
  {
    "text": "氣的媽媽是誰？D，因為D生下氣（低聲下氣）。",
    "category": "諧音梗",
    "author": ""
  },
  {
    "text": "蘋果Apple的表弟是誰？Oppo。",
    "category": "冷笑話",
    "author": ""
  },
  {
    "text": "聖誕節快到了，朋友問我說聖誕節你還是一個人嗎？廢話！難道我會變成一條狗嗎？",
    "category": "生活笑話",
    "author": ""
  },
  {
    "text": "為什麼動物園裡最不能惹的動物是猩猩？因為牠很敲胸（囂張）的。",
    "category": "動物笑話",
    "author": ""
  },
  {
    "text": "一隻北極熊朝我們走過來。有備而來（有bear來）。",
    "category": "諧音梗",
    "author": ""
  },
  {
    "text": "哪種昆蟲最不喜歡被人污辱？蜈蚣，因為蜈蚣不受辱（無功不受祿）。",
    "category": "諧音梗",
    "author": ""
  },
  {
    "text": "小動物們聚餐，為什麼只有小象很生氣？因為這是一個氣象局。",
    "category": "諧音梗",
    "author": ""
  },
  {
    "text": "小明很喜歡坐同一部校車的一位女生，他鼓起勇氣傳紙條給她，紙條上寫著：「如果妳願意跟我交朋友，請把紙條傳回來；如果不願意，請把紙條丟到窗外去。」過了一會兒，女生把紙條慢慢傳回來了，上面寫著：「窗戶打不開！」",
    "category": "學生校園",
    "author": ""
  },
  {
    "text": "小明跟小華約吃飯，結果時間到了小華還沒出現。小明：「你在哪啊？」小華：「我忘記過去了…」小明：「別擔心，你還有現在和未來啊。」",
    "category": "冷笑話",
    "author": ""
  },
  {
    "text": "小明到夜市吃宵夜，看到招牌寫著「花枝意麵」，就叫碗來吃。吃到一半發現根本沒有花枝，就問老闆娘：「我的花枝意麵根本沒花枝啊？」老闆娘：「花枝是我的名字啦！」",
    "category": "台灣特色",
    "author": ""
  },
  {
    "text": "媽媽：「你有關緊窗戶嗎？」小明：「我們家哪有觀景窗。」",
    "category": "諧音梗",
    "author": ""
  },
  {
    "text": "有一天下午，客人到幼稚園參觀，問一個小弟弟：「小弟弟，你午睡了沒？」小弟弟搖搖頭回答：「我四歲，還沒五歲！」",
    "category": "親子家庭",
    "author": ""
  },
  {
    "text": "一年級的老師教小朋友認識家禽動物。老師：「有一種動物兩隻腳，每天早上太陽公公出來時，牠都會叫你起床，是哪一種動物？」小朋友：「媽媽！」",
    "category": "親子家庭",
    "author": ""
  },
  {
    "text": "兒子：「童軍老師說要日行一善，我今天做到了！」母親：「很好啊！說來聽聽。」兒子：「一位郵差伯伯上廁所時，我把他腳踏車上的信件全部都投到郵筒裡。」",
    "category": "親子家庭",
    "author": ""
  },
  {
    "text": "毛利小五郎過暑假，就變成了毛利小六郎。",
    "category": "冷笑話",
    "author": ""
  },
  {
    "text": "老師說：「成功需要五個字：特別能吃苦。」學生說：「那我已經成功五分之四了！」老師問：「怎麼說？」學生答：「因為我特別能吃！」",
    "category": "學生校園",
    "author": ""
  },
  {
    "text": "為什麼在鹽埕不能隨地亂尿尿？因為會尿到鹽（尿道炎）。",
    "category": "台灣特色",
    "author": ""
  },
  {
    "text": "一位年輕人很想獲得自由，跑去問自由女神如何才能得到自由。自由女神說：「你看我自由嗎？」",
    "category": "冷笑話",
    "author": ""
  },
  {
    "text": "有對夫妻結婚多年，丈夫總是忘記一些特別的日子。結婚三十五週年那天，妻子暗示說：「老伴，你知不知道，我們坐在這兩張椅子上已經整整三十五年了？」丈夫放下報紙說：「妳是不是想跟我換位子？」",
    "category": "生活笑話",
    "author": ""
  },
  {
    "text": "最近老婆生病了，我很著急關心地問：「親愛的，藥你吃了沒？」老婆回答：「沒呢，還不餓！」",
    "category": "生活笑話",
    "author": ""
  },
  {
    "text": "有一天郝棒棒、郝美麗、郝帥氣三個人去游泳，結果三個人都溺水了。郝帥氣因為會游泳先把郝美麗救上岸，郝美麗就問：「啊不救郝棒棒？」",
    "category": "諧音梗",
    "author": ""
  },
  {
    "text": "皇帝對身旁的小李子說：「你用一個字來形容朕。」小李子回答：「喳！」（渣）然後小李子就被砍了。",
    "category": "冷笑話",
    "author": ""
  },
  {
    "text": "一個阿姨去醫院打針，護理師：「先深呼吸。」阿姨：「我是小姐。」（先生呼吸）",
    "category": "諧音梗",
    "author": ""
  },
  {
    "text": "一天逛小吃街，發現一家賣蛋撻店。我問店員：「請問這是單賣的嗎？」店員：「不，這是日本的。」（丹麥的）",
    "category": "諧音梗",
    "author": ""
  },
  {
    "text": "我：「爸，我明天要去當兵了。」爸：「把這隻筆的筆蓋打開。」我打開。爸：「蓋回去。」爸：「很好，當你能夠反覆做一件沒意義的事情，就能適應當兵了。」",
    "category": "生活笑話",
    "author": ""
  },
  {
    "text": "年輕人問禪師：「難道世間就沒有愛了嗎？」禪師拿出了一個叉子，什麼也不說。年輕人說：「難道愛情像叉子一樣…」禪師道：「施主，你錯了！人家吵架，關你叉事？」",
    "category": "冷笑話",
    "author": ""
  },
  {
    "text": "巫婆死掉變什麼？Switch（巫-witch，S+witch）。",
    "category": "諧音梗",
    "author": ""
  },
  {
    "text": "企鵝死掉變什麼？鵝，因為他沒氣了。",
    "category": "冷笑話",
    "author": ""
  },
  {
    "text": "圓形、長方形、正方形、三角形相約出去，誰遲到最久？三角形，因為全等三角形（全遲）。",
    "category": "諧音梗",
    "author": ""
  },
  {
    "text": "楊過最愛吃什麼？小籠包（小龍包）。",
    "category": "諧音梗",
    "author": ""
  },
  {
    "text": "達文西密碼上面是什麼？達文西帳號。",
    "category": "冷笑話",
    "author": ""
  },
  {
    "text": "為什麼非洲沒有藥局？因為空腹不能吃藥。",
    "category": "冷笑話",
    "author": ""
  },
  {
    "text": "誰殺了便當？值日生，因為他負責抬便當。",
    "category": "冷笑話",
    "author": ""
  },
  {
    "text": "張雨生家的木頭哪來的？雨生鋸來的（與生俱來）。",
    "category": "諧音梗",
    "author": ""
  },
  {
    "text": "為什麼邊緣人不剪頭髮？因為沒人要理他。",
    "category": "冷笑話",
    "author": ""
  },
  {
    "text": "船長負責開船，水手呢？水手關燈。",
    "category": "冷笑話",
    "author": ""
  },
  {
    "text": "最浪漫的鳥是什麼？候鳥，因為牠會壁咚。",
    "category": "冷笑話",
    "author": ""
  },
  {
    "text": "警察爆氣變什麼？警報器。",
    "category": "諧音梗",
    "author": ""
  },
  {
    "text": "胃最多能塞幾道菜？九道，因為胃食道逆流。",
    "category": "諧音梗",
    "author": ""
  },
  {
    "text": "剪刀有什麼就能打贏石頭？聯絡簿（布）。",
    "category": "冷笑話",
    "author": ""
  },
  {
    "text": "一百個男人無法抬起的物體，卻有一女子可單手舉起，是什麼？雞蛋。",
    "category": "腦筋急轉彎",
    "author": ""
  },
  {
    "text": "打什麼東西既不花力氣，又很舒服？打瞌睡。",
    "category": "腦筋急轉彎",
    "author": ""
  },
  {
    "text": "廁所裡應該擺什麼花？五月花。",
    "category": "腦筋急轉彎",
    "author": ""
  },
  {
    "text": "人的長壽秘訣是什麼？保持呼吸，不要斷氣。",
    "category": "腦筋急轉彎",
    "author": ""
  },
  {
    "text": "當哥倫布一隻腳邁上新大陸後，緊接著做什麼？邁另一隻腳。",
    "category": "腦筋急轉彎",
    "author": ""
  },
  {
    "text": "世界上除了火車，什麼車最長？塞車。",
    "category": "腦筋急轉彎",
    "author": ""
  },
  {
    "text": "醫治暈車的最好辦法是什麼？不坐車。",
    "category": "腦筋急轉彎",
    "author": ""
  },
  {
    "text": "每個人睡覺前，一定不會忘記的事是什麼？閉上眼睛。",
    "category": "腦筋急轉彎",
    "author": ""
  },
  {
    "text": "什麼辦法能使眉毛長在眼睛下面？倒立。",
    "category": "腦筋急轉彎",
    "author": ""
  },
  {
    "text": "牛頓在蘋果樹下被蘋果擊中，發現了地心引力。如果你坐在椰子樹下等待被椰子打中，你會發現什麼？會發現這種行為很愚蠢。",
    "category": "腦筋急轉彎",
    "author": ""
  },
  {
    "text": "黑頭髮有什麼好處？不怕曬黑。",
    "category": "腦筋急轉彎",
    "author": ""
  },
  {
    "text": "你知道現代的科學家一般都出生在哪嗎？醫院裡。",
    "category": "腦筋急轉彎",
    "author": ""
  },
  {
    "text": "豆腐為什麼能打傷人？因為是凍豆腐。",
    "category": "腦筋急轉彎",
    "author": ""
  },
  {
    "text": "一顆心值多少錢？一億，因為一心一意嘛。",
    "category": "諧音梗",
    "author": ""
  },
  {
    "text": "「小學到大學」要念多久？不到三秒。",
    "category": "腦筋急轉彎",
    "author": ""
  },
  {
    "text": "什麼東西看不到卻可以摸到，萬一摸不到會把人嚇到？脈搏。",
    "category": "腦筋急轉彎",
    "author": ""
  },
  {
    "text": "什麼書你不可能在書店裡買到？秘書。",
    "category": "腦筋急轉彎",
    "author": ""
  },
  {
    "text": "為什麼飛機飛那麼高都不會撞到星星呢？因為星星會「閃」。",
    "category": "腦筋急轉彎",
    "author": ""
  },
  {
    "text": "請問世界上最小的島是什麼島？安全島。",
    "category": "腦筋急轉彎",
    "author": ""
  },
  {
    "text": "哪一個月有二十八天？每個月都有二十八天。",
    "category": "腦筋急轉彎",
    "author": ""
  },
  {
    "text": "「笑」和「哭」有什麼相同之處？都是十畫。",
    "category": "腦筋急轉彎",
    "author": ""
  },
  {
    "text": "人為什麼要走去床上睡覺呢？床不會自己走過來。",
    "category": "腦筋急轉彎",
    "author": ""
  },
  {
    "text": "睡美人最怕什麼？失眠。",
    "category": "腦筋急轉彎",
    "author": ""
  },
  {
    "text": "報紙上登的消息未必都是真的，但什麼消息絕對假不了？日期。",
    "category": "腦筋急轉彎",
    "author": ""
  },
  {
    "text": "「先天」是指父母的遺傳，那「後天」是什麼？明天的明天。",
    "category": "腦筋急轉彎",
    "author": ""
  },
  {
    "text": "什麼東西經常會來，但卻從沒真正來過？明天。",
    "category": "腦筋急轉彎",
    "author": ""
  },
  {
    "text": "什麼樣的河人們永遠也渡不過去？銀河。",
    "category": "腦筋急轉彎",
    "author": ""
  },
  {
    "text": "一塊三分熟的牛排在街上走著，突然看到一塊五分熟的牛排，可卻沒有理會他。為什麼？因為他們不熟。",
    "category": "冷笑話",
    "author": ""
  },
  {
    "text": "一頭牛向北走十米，再向西走十米，再向南走十米，倒退右轉，問牛的尾巴朝哪兒？朝地。",
    "category": "腦筋急轉彎",
    "author": ""
  },
  {
    "text": "哪個歐洲國家的生意不批發？丹麥（單賣）。",
    "category": "諧音梗",
    "author": ""
  },
  {
    "text": "進浴室洗澡時，要先脫衣服還是褲子？先關門比較好。",
    "category": "腦筋急轉彎",
    "author": ""
  },
  {
    "text": "哪一種動物你打了牠卻流了自己的血？蚊子。",
    "category": "腦筋急轉彎",
    "author": ""
  },
  {
    "text": "誰是獸中之王？動物園園長。",
    "category": "腦筋急轉彎",
    "author": ""
  },
  {
    "text": "把8分成兩半，是多少？零，上下切開變成兩個零。",
    "category": "腦筋急轉彎",
    "author": ""
  },
  {
    "text": "青蛙為什麼能跳得比樹高？樹不會跳。",
    "category": "腦筋急轉彎",
    "author": ""
  },
  {
    "text": "如果有一輛車，司機是王子，乘客是公主，請問這輛車是誰的？「如果」的。",
    "category": "腦筋急轉彎",
    "author": ""
  },
  {
    "text": "世界上什麼人一下子變老？新娘，因為今天是新娘，明天是老婆。",
    "category": "腦筋急轉彎",
    "author": ""
  },
  {
    "text": "要考試了，不能看什麼書？百科全書（百科全輸）。",
    "category": "諧音梗",
    "author": ""
  },
  {
    "text": "什麼時候有人敲門，你絕不會說請進？在廁所裡的時候。",
    "category": "腦筋急轉彎",
    "author": ""
  },
  {
    "text": "一張桌子有四個角，砍去一個角，還剩幾個角？五個。",
    "category": "腦筋急轉彎",
    "author": ""
  },
  {
    "text": "日月潭的中間是什麼？是「月」字。",
    "category": "腦筋急轉彎",
    "author": ""
  },
  {
    "text": "用什麼可以解開所有的謎？答案。",
    "category": "腦筋急轉彎",
    "author": ""
  },
  {
    "text": "龜兔賽跑，請豬來當裁判，請問龜兔誰會贏？不能說！說的人是豬。",
    "category": "腦筋急轉彎",
    "author": ""
  },
  {
    "text": "公司裁員時不能喝什麼？仙草蜜，因為「先炒me」。",
    "category": "職場笑話",
    "author": ""
  },
  {
    "text": "獅子、老虎、斑馬，誰最愛亂買東西？斑馬！因為牠是「黑白買」嘛。",
    "category": "諧音梗",
    "author": ""
  },
  {
    "text": "糖果是公的還是母的？母的，因為它會生螞蟻。",
    "category": "腦筋急轉彎",
    "author": ""
  },
  {
    "text": "哆啦A夢裡哪個角色長大會成為醫生？小夫，因為長大變大夫。",
    "category": "諧音梗",
    "author": ""
  },
  {
    "text": "是太陽叫公雞起床，還是公雞叫太陽起床？是公雞叫太陽起床，因為太陽不會叫。",
    "category": "腦筋急轉彎",
    "author": ""
  },
  {
    "text": "有一種水果沒吃之前是綠色的，吃下去是紅色的，吐出時卻是黑色的，這是什麼水果？西瓜。",
    "category": "腦筋急轉彎",
    "author": ""
  },
  {
    "text": "參加考試時，除了准考證之外，最重要的是什麼？記得起床。",
    "category": "學生校園",
    "author": ""
  },
  {
    "text": "海水為什麼是鹹的？魚流的淚太多了。",
    "category": "冷笑話",
    "author": ""
  },
  {
    "text": "哪一件衣服最耐穿？最不喜歡的那件。",
    "category": "冷笑話",
    "author": ""
  },
  {
    "text": "什麼東西不能用放大鏡放大？角度。",
    "category": "腦筋急轉彎",
    "author": ""
  },
  {
    "text": "做什麼事睜一隻眼閉一隻眼比較好？拍照的時候。",
    "category": "腦筋急轉彎",
    "author": ""
  },
  {
    "text": "樹上有一百隻鳥，用什麼方法才能把牠們全部抓住？用照相機。",
    "category": "腦筋急轉彎",
    "author": ""
  },
  {
    "text": "阿忠結婚好幾年了，卻沒生下一個孩子，這是為什麼？他生的是雙胞胎。",
    "category": "腦筋急轉彎",
    "author": ""
  },
  {
    "text": "天上有十個太陽，為什麼后羿只射下九個？他不想摸黑回家。",
    "category": "腦筋急轉彎",
    "author": ""
  },
  {
    "text": "什麼事你明明沒有做卻要受罰？做作業。",
    "category": "學生校園",
    "author": ""
  },
  {
    "text": "當跳到黃河也洗不清的時候，該如何澄清自己？跳到澄清湖裡。",
    "category": "台灣特色",
    "author": ""
  },
  {
    "text": "為什麼夏天才有颱風？因為它要冬眠。",
    "category": "冷笑話",
    "author": ""
  },
  {
    "text": "一家洗衣店招牌寫著「二十四小時交貨」，今天小高拿去洗，為何老闆說要三天後才能拿？因為每天工作八小時，三天正好二十四小時。",
    "category": "生活笑話",
    "author": ""
  },
  {
    "text": "什麼叫做「緩兵之計」？改天再告訴你。",
    "category": "冷笑話",
    "author": ""
  },
  {
    "text": "生了病，打針跟吃藥哪一種比較痛苦？細菌比較痛苦。",
    "category": "腦筋急轉彎",
    "author": ""
  },
  {
    "text": "你身上的什麼東西用右手去拿永遠拿不到？右手。",
    "category": "腦筋急轉彎",
    "author": ""
  },
  {
    "text": "用什麼擦地最乾淨？用力。",
    "category": "腦筋急轉彎",
    "author": ""
  },
  {
    "text": "小華說他能在一秒鐘之內把房間和房間裡的玩具都變沒了，這可能嗎？把眼睛閉上。",
    "category": "腦筋急轉彎",
    "author": ""
  },
  {
    "text": "比細菌還小的東西是什麼？細菌的兒子。",
    "category": "冷笑話",
    "author": ""
  },
  {
    "text": "藍色的筆能寫出紅字嗎？寫個「紅」字當然可以。",
    "category": "腦筋急轉彎",
    "author": ""
  },
  {
    "text": "為什麼暑假一定比寒假長？熱漲冷縮。",
    "category": "腦筋急轉彎",
    "author": ""
  },
  {
    "text": "什麼官不僅不領工資，還要自掏腰包？新郎官。",
    "category": "腦筋急轉彎",
    "author": ""
  },
  {
    "text": "為什麼一瓶標明劇毒的藥對人卻無害？只要你不去喝它。",
    "category": "腦筋急轉彎",
    "author": ""
  },
  {
    "text": "怎麼稱讚皮膚很黑的人？你不膚淺。",
    "category": "冷笑話",
    "author": ""
  },
  {
    "text": "外國人搭著你的肩膀問：「這裡是故宮嗎？」你回答：「不，這是我的肩膀。」",
    "category": "冷笑話",
    "author": ""
  },
  {
    "text": "鎖匠跟大學生誰學歷比較高？鎖匠，因為他研究鎖（研究所）。",
    "category": "諧音梗",
    "author": ""
  },
  {
    "text": "禿頭的人適合看鬼片，因為會讓他們頭皮發毛。",
    "category": "冷笑話",
    "author": ""
  },
  {
    "text": "丁丁懷孕了會變成什麼？ㄛㄛ。",
    "category": "冷笑話",
    "author": ""
  },
  {
    "text": "史上最愛吃零食的總統是誰？袁世凱，因為他是臨時大總統（零食大總統）。",
    "category": "諧音梗",
    "author": ""
  },
  {
    "text": "有隻熊剪了指甲就變成了「能」。",
    "category": "冷笑話",
    "author": ""
  },
  {
    "text": "警衛在笑什麼？警衛在校門口（笑門口）。",
    "category": "諧音梗",
    "author": ""
  },
  {
    "text": "舉重選手抓舉失敗遭淘汰會說什麼？「真重，再見。」",
    "category": "諧音梗",
    "author": ""
  },
  {
    "text": "小明打電話給客服，客服說：「很高興為您服務。」小明：「您高興得太早了。」",
    "category": "生活笑話",
    "author": ""
  },
  {
    "text": "芥末走在路上被打了一巴掌，路人說：「啊你不是很嗆？」",
    "category": "冷笑話",
    "author": ""
  },
  {
    "text": "為什麼綁架都要綁架模範生？因為他一副好榜（綁）樣。",
    "category": "諧音梗",
    "author": ""
  },
  {
    "text": "一顆星星有多重？八克，因為星巴克。",
    "category": "諧音梗",
    "author": ""
  },
  {
    "text": "去年夏天我去夏威夷，結果威夷就被嚇到了。",
    "category": "諧音梗",
    "author": ""
  },
  {
    "text": "青蛙吃了什麼之後不會叫？冬瓜，因為Don't呱。",
    "category": "諧音梗",
    "author": ""
  },
  {
    "text": "佩奇跟媽媽說朋友說她長得像吹風機，媽媽說：「講話就講話，不要對媽媽吹。」",
    "category": "冷笑話",
    "author": ""
  },
  {
    "text": "老人照鏡子會看到什麼？老樣子。",
    "category": "冷笑話",
    "author": ""
  },
  {
    "text": "誰的大便是圓的？原屎人（原始人）。",
    "category": "諧音梗",
    "author": ""
  },
  {
    "text": "甲：「女友什麼條件都比我好，怎麼辦？」乙：「至少她眼光比你差。」",
    "category": "生活笑話",
    "author": ""
  },
  {
    "text": "唐代奴才：「喏。」清代奴才：「喳。」現代奴才：「收到。」",
    "category": "職場笑話",
    "author": ""
  },
  {
    "text": "女星：「我一天只睡三小時。」記者：「那你大部分時間都在做什麼？」女星：「打瞌睡。」",
    "category": "冷笑話",
    "author": ""
  },
  {
    "text": "小華因為長得像女孩子，國小六年來每天都有一個男同學幫他拿書包。後來小華剪了短髮恢復男兒本色，最吃驚的是那個每天幫他拿書包的男同學。",
    "category": "學生校園",
    "author": ""
  },
  {
    "text": "遊客在遊覽車上拍司機肩膀嚇到他，司機說：「別嚇我，我以前開靈車的。」",
    "category": "生活笑話",
    "author": ""
  },
  {
    "text": "學生把「逝者如斯夫」翻譯成：「死去的那個人好像是我的丈夫。」",
    "category": "學生校園",
    "author": ""
  },
  {
    "text": "老師叫旁邊的同學叫醒睡覺的人，同學說：「是你自己把他弄睡著的，你自己去叫。」",
    "category": "學生校園",
    "author": ""
  },
  {
    "text": "六歲的小美被班上男生求婚，媽媽問：「他有固定工作嗎？」小美說：「有，他負責擦黑板。」",
    "category": "親子家庭",
    "author": ""
  },
  {
    "text": "超市裡丈夫跟一位年輕女性說：「我老婆不見了，但是每次看我跟別的女人講話她就會自己出現。」",
    "category": "生活笑話",
    "author": ""
  },
  {
    "text": "阿公叫孫子「插插頭」，孫子就跑進浴室拿毛巾幫阿公擦頭。",
    "category": "親子家庭",
    "author": ""
  },
  {
    "text": "病患在精神病院討論電話簿，說這是一部「曠世鉅作」，但出場人物太多情節看不太懂。護理師叫他們放回電話簿。",
    "category": "生活笑話",
    "author": ""
  },
  {
    "text": "有一天小明跟小恩騎腳踏車，小明想偷牽小恩的手就說：「小恩，把手給我。」然後小恩就把腳踏車的「把手」拆下來給小明了。",
    "category": "冷笑話",
    "author": ""
  },
  {
    "text": "孩子第一天上學回來說：「我喜歡去上學，也喜歡放學，可是不喜歡中間的時間。」",
    "category": "親子家庭",
    "author": ""
  },
  {
    "text": "父親告訴兒子家裡添了小弟弟，兒子說：「請幫我拿書包，我要去告訴媽媽。」",
    "category": "親子家庭",
    "author": ""
  },
  {
    "text": "丈夫在許願池許願，太太許完後，丈夫許願：「希望我付得起太太願望裡所有東西的價錢。」",
    "category": "生活笑話",
    "author": ""
  },
  {
    "text": "老公結婚二十周年終於說：「我養你比你爸爸養你還多了一年。」",
    "category": "生活笑話",
    "author": ""
  },
  {
    "text": "計程車司機闖紅燈解釋：「我哥哥總是這樣開。」到了綠燈卻停車，說：「我哥哥可能從對面開來。」",
    "category": "生活笑話",
    "author": ""
  },
  {
    "text": "大學布告欄上寫著：「教科書出售，九成新，幾乎沒有用過，成績單為證。」",
    "category": "學生校園",
    "author": ""
  },
  {
    "text": "夜深了，孩子睡覺時哭了起來。父親決定唱催眠曲哄他。結果隔壁傳來抗議聲：「還是讓孩子哭吧！」",
    "category": "親子家庭",
    "author": ""
  },
  {
    "text": "小文對計程車司機抱怨：「搭你的車好無聊，都沒有音樂。」司機回：「那我建議妳搭垃圾車。」",
    "category": "生活笑話",
    "author": ""
  },
  {
    "text": "四十歲女生條件不錯卻未婚，小明問為何不結婚，她答：「我小時候田徑隊受傷，腳底有疤。」小明困惑，她說：「對啊，那我結不結婚關你什麼事？」",
    "category": "生活笑話",
    "author": ""
  },
  {
    "text": "老師：「請舉例說明熱漲冷縮現象。」學生：「寒假四星期，暑假八星期。」",
    "category": "學生校園",
    "author": ""
  },
  {
    "text": "婦人：「醫生，我體重超過九十公斤，怎麼辦？」醫生：「做頭部運動，左右搖擺。有人請你吃東西時就做，直到那人離開。」",
    "category": "生活笑話",
    "author": ""
  },
  {
    "text": "小明在KTV不小心按到「切歌」，切掉的正好是老闆唱的歌。小明解釋：「我以為是導唱，沒人唱，所以就切了。」",
    "category": "職場笑話",
    "author": ""
  },
  {
    "text": "新兵訓練中心，班長教士兵投手榴彈說：「投出去後一定要馬上臥倒，如果不臥倒，你們知道會怎樣！」新兵齊聲說：「班長會罵！」",
    "category": "生活笑話",
    "author": ""
  },
  {
    "text": "汽車會飛叫什麼？咖啡（Car飛）。",
    "category": "諧音梗",
    "author": ""
  },
  {
    "text": "鴨子坐計程車叫什麼？小黃瓜。",
    "category": "諧音梗",
    "author": ""
  },
  {
    "text": "木魚掉海裡變什麼？虱目魚。",
    "category": "諧音梗",
    "author": ""
  },
  {
    "text": "打電話給烏龜叫什麼？苦瓜（call龜）。",
    "category": "諧音梗",
    "author": ""
  },
  {
    "text": "地瓜笑了變什麼？地瓜球（台語：地瓜啾）。",
    "category": "諧音梗",
    "author": ""
  },
  {
    "text": "十隻羊站在不同的位置猜一成語？抑揚頓挫（一羊蹲坐）。",
    "category": "諧音梗",
    "author": ""
  },
  {
    "text": "牛游完泳上岸之後變什麼？有勇無謀（有泳無毛）。",
    "category": "諧音梗",
    "author": ""
  },
  {
    "text": "小明放屁為什麼很大聲？因為他穿喇叭褲。",
    "category": "冷笑話",
    "author": ""
  },
  {
    "text": "三年級學生說不用讀書了，因為「懂得東西夠多了」，他要做二年級老師。",
    "category": "親子家庭",
    "author": ""
  },
  {
    "text": "我問禪師：「大師，我本來就黑，一到夏天曬得更黑，別人都取笑我怎麼辦？」大師不言語，悠悠把寺門打開讓陽光照進來。「我明白了大師…」「不是，老衲只是想看清楚，施主你到底在哪！」",
    "category": "冷笑話",
    "author": ""
  },
  {
    "text": "病患訴說失去了愛情、親情、友情和金錢，護士回應：「你不是還有病嗎！」",
    "category": "冷笑話",
    "author": ""
  },
  {
    "text": "有人申請「能力公司」的營業執照，結果被登記為「能力有限公司」。",
    "category": "職場笑話",
    "author": ""
  },
  {
    "text": "焊武帝、糖太宗、漢糕祖幾家店互相沉默不語，直到看到寫著「擒屎皇」的拉糞車經過。",
    "category": "台灣特色",
    "author": ""
  },
  {
    "text": "某天洋蔥對春風說：「Google資料怎麼那麼難查。」春風：「要關鍵字啦。」洋蔥就報警把建志抓去關了。",
    "category": "諧音梗",
    "author": ""
  },
  {
    "text": "有一天我去影印店影印，老闆問：「想印怎樣呢？」我：「照框印吧。」老闆就印了一個宋太祖給我（趙匡胤）。",
    "category": "諧音梗",
    "author": ""
  },
  {
    "text": "小智參加神奇寶貝大賽到最終分組，裁判問想報名哪種屬性。小智說：「我可以報雷嗎？」然後就被觀眾圍毆了。",
    "category": "冷笑話",
    "author": ""
  },
  {
    "text": "歷史課老師問打瞌睡的學生「清廷最大的敵人是什麼」，學生迷迷糊糊答：「青蛙。」",
    "category": "學生校園",
    "author": ""
  },
  {
    "text": "老師出哲學考題「什麼是勇氣」，學生只寫了「這就是勇氣」就交卷了。",
    "category": "學生校園",
    "author": ""
  },
  {
    "text": "剛剛吃了起司後我突然變得很強壯，因為芝士就是力量（知識就是力量）。",
    "category": "諧音梗",
    "author": ""
  },
  {
    "text": "辛巴姓什麼？王，因為獅子王辛巴。",
    "category": "冷笑話",
    "author": ""
  },
  {
    "text": "小明走著進超商，坐輪椅出來，為什麼？因為他繳費了（腳廢了）。",
    "category": "諧音梗",
    "author": ""
  },
  {
    "text": "阮經天的舅公叫什麼名字？阮（軟）骨功。",
    "category": "諧音梗",
    "author": ""
  },
  {
    "text": "亞洲舞王是羅志祥，台灣舞后是誰？雷陣雨。",
    "category": "諧音梗",
    "author": ""
  },
  {
    "text": "死掉的腎猜一本小說？西遊記（台語）。",
    "category": "諧音梗",
    "author": ""
  },
  {
    "text": "小明上課喝飲料被老師罵：「喝喝喝喝喝喝喝喝！」小明回：「你笑屁啊！」",
    "category": "學生校園",
    "author": ""
  },
  {
    "text": "掛號護士問病人電話「掛了沒」，病人嚇一跳以為自己要掛了。",
    "category": "生活笑話",
    "author": ""
  },
  {
    "text": "台北老夫妻想兒女回家過年，就互相傳訊說要離婚。結果兒女都趕回來了。",
    "category": "親子家庭",
    "author": ""
  },
  {
    "text": "景氣差的時候公司發勞動節禮物：一條毛巾。因為老闆說「做到流汗嫌到流涎」。",
    "category": "職場笑話",
    "author": ""
  },
  {
    "text": "被按喇叭的女駕駛下車對後面駕駛說：「你來開，我幫你按。」",
    "category": "生活笑話",
    "author": ""
  },
  {
    "text": "司機讀了一些書之後叫老闆起床說：「時辰到了。」",
    "category": "職場笑話",
    "author": ""
  },
  {
    "text": "忘情水是誰給的？啊哈。（啊哈，給我一杯忘情水）",
    "category": "諧音梗",
    "author": ""
  },
  {
    "text": "為什麼尾牙有姓余的同事在比較好玩？因為他們可以帶來余姓節目（餘興節目）。",
    "category": "職場笑話",
    "author": ""
  },
  {
    "text": "去台灣哪個地方比較不容易看到當地人穿裙子、高跟鞋？南庄（男裝）。",
    "category": "台灣特色",
    "author": ""
  },
  {
    "text": "什麼時候一加一不等於二？算錯的時候。",
    "category": "腦筋急轉彎",
    "author": ""
  },
  {
    "text": "一大早走在路上遇到小麻雀，我說：「小麻雀，你相信我很帥嗎？」小麻雀：「我相信！」我：「哈，一大早就有小確信。」",
    "category": "諧音梗",
    "author": ""
  },
  {
    "text": "救生員說他救過無數個人，其中一個成為他老婆。朋友問有何感想，他嘆：「她的人生浮起來了，我的人生沉下去了。」",
    "category": "生活笑話",
    "author": ""
  },
  {
    "text": "醫學院口試，學生把藥物劑量搞錯了，教授說：「病人已於三十秒前因過量去世了。」",
    "category": "學生校園",
    "author": ""
  },
  {
    "text": "仙人掌最喜歡什麼休閒活動？針灸。",
    "category": "冷笑話",
    "author": ""
  },
  {
    "text": "哪牌冷氣吹了會瘦？日立，因為日立變頻冷氣，消瘦第一。",
    "category": "諧音梗",
    "author": ""
  },
  {
    "text": "為什麼軍中的早餐一直是豆漿饅頭，從不吃稀飯？饅頭比較好數。",
    "category": "冷笑話",
    "author": ""
  },
  {
    "text": "每對夫妻在生活中都有一個絕對的共同點是什麼？同年同月同日結婚。",
    "category": "腦筋急轉彎",
    "author": ""
  },
  {
    "text": "廢除早自習會造成什麼影響？少睡半小時。",
    "category": "學生校園",
    "author": ""
  },
  {
    "text": "一個圓有幾個面？兩個面，一個外面一個裡面。",
    "category": "腦筋急轉彎",
    "author": ""
  },
  {
    "text": "胖胖是個頗有名氣的跳水運動員，可是有一天他站在跳台上卻不敢往下跳，為什麼？因為水池裡沒有水。",
    "category": "腦筋急轉彎",
    "author": ""
  },
  {
    "text": "電視對人類最大的貢獻是什麼？讓世界瞭解了準時的好處。",
    "category": "冷笑話",
    "author": ""
  },
  {
    "text": "藝人方芳和方芳芳有什麼關係？一個是方的平方，一個是方的立方。",
    "category": "冷笑話",
    "author": ""
  },
  {
    "text": "考試做判斷題，小花擲骰子決定答案，但題目有二十題，為什麼她卻扔了四十次？她要驗算一遍。",
    "category": "學生校園",
    "author": ""
  },
  {
    "text": "永遠都沒有終結的事是什麼？問題。",
    "category": "冷笑話",
    "author": ""
  },
  {
    "text": "胖姐站上體重秤時，為何指針只指著五？指針已經轉過一圈了。",
    "category": "冷笑話",
    "author": ""
  },
  {
    "text": "「狗會汪，貓會喵，雞呢？」「雞會留給準備好的人。」（機會留給準備好的人）",
    "category": "諧音梗",
    "author": ""
  },
  {
    "text": "有天貝殼回老家，跟他媽講什麼？I'm back（我是貝殼）。",
    "category": "諧音梗",
    "author": ""
  },
  {
    "text": "哪個牌子的車最沒種？Nissan（你算了）。",
    "category": "諧音梗",
    "author": ""
  },
  {
    "text": "哪個殺手只會講英文？銀翼殺手（English）。",
    "category": "諧音梗",
    "author": ""
  },
  {
    "text": "小鹿叫班比，大鹿呢？尋奇。",
    "category": "冷笑話",
    "author": ""
  },
  {
    "text": "年年有餘為何存不到錢？因為年年都被炒魷魚。",
    "category": "諧音梗",
    "author": ""
  },
  {
    "text": "暖暖包為什麼有鐵粉？因為它有鐵粉（忠實粉絲）。",
    "category": "冷笑話",
    "author": ""
  }
]
